bearing/__init__.py
bearing/datasets/__init__.py
bearing/datasets/cwru/__init__.py
bearing/datasets/jnu/__init__.py
bearing/datasets/pu/__init__.py
bearing/transform/__init__.py
bearing_python-1.0.4.dist-info/METADATA
bearing_python-1.0.4.dist-info/WHEEL
bearing_python-1.0.4.dist-info/entry_points.txt
bearing_python-1.0.4.dist-info/top_level.txt
bearing_python-1.0.4.dist-info/RECORD
