Metadata-Version: 2.1
Name: bearing-python
Version: 1.0.4
Summary: README.md
Home-page: https://github.com/fonderxu/Bearing-fault-diagnosis-datasets
Author: Xu Fangzheng
Author-email: fonderxu@163.com
License: UNKNOWN
Platform: UNKNOWN
